Metadata-Version: 2.1
Name: zen_logging
Version: 1.1.0
Summary: Zen logging, a simple python logging library that extends logging.
Author-email: Desultory <dev@pyl.onl>
Project-URL: Homepage, https://github.com/desultory/zen-logging
Project-URL: Issues, https://github.com/desultory/zen-logging/issues
Classifier: Programming Language :: Python :: 3
Classifier: License :: OSI Approved :: GNU General Public License v2 (GPLv2)
Classifier: Operating System :: OS Independent
Requires-Python: >=3.9
License-File: LICENSE
